llama_index/readers/database/__init__.py
llama_index/readers/database/base.py
llama_index_readers_database-0.5.1.dist-info/METADATA
llama_index_readers_database-0.5.1.dist-info/WHEEL
llama_index_readers_database-0.5.1.dist-info/licenses/LICENSE
llama_index_readers_database-0.5.1.dist-info/RECORD
