Metadata-Version: 2.4
Name: llama-index-readers-database
Version: 0.5.1
Summary: llama-index readers database integration
Author-email: Your Name <you@example.com>
Maintainer: kevinqz
License-Expression: MIT
License-File: LICENSE
Keywords: aws rds,postgres,snowflake,sql
Requires-Python: <4.0,>=3.9
Requires-Dist: llama-index-core<0.15,>=0.13.0
